fastdds/__init__.py
fastdds/_fastdds_python.so
fastdds/libfastcdr.so.2
fastdds/libfastdds.so.3.0
fastdds/libtinyxml2.so.9
fourier_aurora_client/__init__.py
fourier_aurora_client/aurora_state_map.py
fourier_aurora_client/client.py
fourier_aurora_client/dds_interface.py
fourier_aurora_client/qos_profile.py
fourier_dds_msgs_lib/libAccel.so
fourier_dds_msgs_lib/libAccelStamped.so
fourier_dds_msgs_lib/libAccelWithCovariance.so
fourier_dds_msgs_lib/libAccelWithCovarianceStamped.so
fourier_dds_msgs_lib/libAlgorithmCmd.so
fourier_dds_msgs_lib/libAuroraCmd.so
fourier_dds_msgs_lib/libAuroraState.so
fourier_dds_msgs_lib/libAurorapyMsg.so
fourier_dds_msgs_lib/libBaseData.so
fourier_dds_msgs_lib/libBaseStructType.so
fourier_dds_msgs_lib/libBatteryState.so
fourier_dds_msgs_lib/libCalculator.so
fourier_dds_msgs_lib/libCameraInfo.so
fourier_dds_msgs_lib/libChannelFloat32.so
fourier_dds_msgs_lib/libCompressedImage.so
fourier_dds_msgs_lib/libContactData.so
fourier_dds_msgs_lib/libDuration.so
fourier_dds_msgs_lib/libErrorCodes.so
fourier_dds_msgs_lib/libFluidPressure.so
fourier_dds_msgs_lib/libGetMap.so
fourier_dds_msgs_lib/libGetPlan.so
fourier_dds_msgs_lib/libGrantTouchFeedbackCmd.so
fourier_dds_msgs_lib/libGrcsRequest.so
fourier_dds_msgs_lib/libGridCells.so
fourier_dds_msgs_lib/libHeadMediaCmd.so
fourier_dds_msgs_lib/libHeader.so
fourier_dds_msgs_lib/libIlluminance.so
fourier_dds_msgs_lib/libImage.so
fourier_dds_msgs_lib/libImu.so
fourier_dds_msgs_lib/libInertia.so
fourier_dds_msgs_lib/libInertiaStamped.so
fourier_dds_msgs_lib/libJointState.so
fourier_dds_msgs_lib/libJointTrajectory.so
fourier_dds_msgs_lib/libJointTrajectoryPoint.so
fourier_dds_msgs_lib/libJoy.so
fourier_dds_msgs_lib/libJoyFeedback.so
fourier_dds_msgs_lib/libJoyFeedbackArray.so
fourier_dds_msgs_lib/libLaserEcho.so
fourier_dds_msgs_lib/libLaserScan.so
fourier_dds_msgs_lib/libLedActionCmd.so
fourier_dds_msgs_lib/libLoadMap.so
fourier_dds_msgs_lib/libLocomotionCmd.so
fourier_dds_msgs_lib/libMagneticField.so
fourier_aurora_client-0.1.1.dist-info/METADATA
fourier_aurora_client-0.1.1.dist-info/WHEEL
fourier_aurora_client-0.1.1.dist-info/top_level.txt
fourier_aurora_client-0.1.1.dist-info/RECORD
