Metadata-Version: 2.4
Name: fourier-aurora-client
Version: 0.1.1
Summary: Aurora Python Client - Python client for the Aurora API
Author-email: James <qianyue.zhang@fftai.com>
Requires-Python: >=3.8
Provides-Extra: dev
Requires-Dist: pytest; extra == "dev"
Requires-Dist: pytest-cov; extra == "dev"
Requires-Dist: black; extra == "dev"
Requires-Dist: isort; extra == "dev"
Requires-Dist: flake8; extra == "dev"
